{
  "author": "Nayan",
  "autoRestart": true,
  "accpetPending": false,
  "developermode": false,
  "language": "en",
  "notification": true,
  "approval": false,
  "BOTNAME": "SAIM-BOT",
  "PREFIX": "!",
  "OPERATOR": [
    "845455655575",
    "845455655575"
  ],
  "ADMINBOT": [
    "845455655575",
    ""
  ],
  "OWNER": ["845455655575"], 
  "APPROVED": [845455655575],
  "disabledcmds": [],
  "disabledevents": [],
  "note": "make sure that the bot name you entered is all lowercase",
  "notice": "dont cng author name and owner uid. otherwise bot not working"
}
